echofire/__init__.py
echofire/cli/__init__.py
echofire/cli/main.py
echofire/core/__init__.py
echofire/core/interactive.py
echofire/core/report.py
echofire/core/testing.py
echofire/models/__init__.py
echofire/models/config_model.py
echofire/models/interactive_models.py
echofire/models/testing_models.py
echofire/models/tracing_models.py
echofire/static/index.html
echofire/utils/__init__.py
echofire/utils/config.py
echofire/utils/env.py
echofire-0.1.18.dist-info/METADATA
echofire-0.1.18.dist-info/WHEEL
echofire-0.1.18.dist-info/entry_points.txt
echofire-0.1.18.dist-info/RECORD
