Metadata-Version: 2.1
Name: echofire
Version: 0.1.18
Summary: Realistic Voice Agent Testing - Automate end-to-end evaluation of voice agents with human-like audio simulation
Author: Dylan Huang
Author-email: dhuang@fireworks.ai
Requires-Python: >=3.9,<4.0
Classifier: Programming Language :: Python :: 3
Classifier: Programming Language :: Python :: 3.9
Classifier: Programming Language :: Python :: 3.10
Classifier: Programming Language :: Python :: 3.11
Requires-Dist: aiofiles (>=23.0.0,<24.0.0)
Requires-Dist: asyncio (>=3.4.3,<4.0.0)
Requires-Dist: dotenv (>=0.9.9,<0.10.0)
Requires-Dist: human-id (>=0.2.0,<0.3.0)
Requires-Dist: numpy (>=1.24.0,<2.0.0)
Requires-Dist: openai (>=1.0.0,<2.0.0)
Requires-Dist: pydantic (>=2.0.0,<3.0.0)
Requires-Dist: pyyaml (>=6.0.2,<7.0.0)
Requires-Dist: rich (>=13.0.0,<14.0.0)
Requires-Dist: scipy (>=1.10.0,<2.0.0)
Requires-Dist: sounddevice (>=0.4.6,<0.5.0)
Requires-Dist: soundfile (>=0.12.1,<0.13.0)
Requires-Dist: typer (>=0.15.2,<0.16.0)
Requires-Dist: websockets (>=11.0.0,<12.0.0)
